Metadata-Version: 2.4
Name: htmlcmp
Version: 1.0.18
Summary: Compare HTML files by rendered output
Author: Andreas Stefl
Maintainer-email: Andreas Stefl <stefl.andreas@gmail.com>
Project-URL: homepage, https://opendocument.app/
Project-URL: source, https://github.com/opendocument-app/compare-html
Project-URL: download, https://pypi.org/project/pyodr/#files
Project-URL: tracker, https://github.com/opendocument-app/compare-html/issues
Project-URL: release notes, https://github.com/opendocument-app/compare-html/releases
Requires-Python: >=3.7
Requires-Dist: pillow
Requires-Dist: selenium
Requires-Dist: flask
Requires-Dist: watchdog
